{
  "loading": "Sto caricando MadelineProto...",
  "loaded": "MadelineProto caricato!",
  "ask_phone_number": "Inserisci il numero di telefono: ",
  "ask_login_code": "Inserisci il codice ricevuto: ",
  "ask_2fa_password": "Inserisci la password della verifica in due passaggi: ",
  "ask_name": "Inserisci il nome: ",
  "session_loaded": "Sessione caricata!",
  "error": "Errore: ",
  "background": "TGUserbot avviato in background.",
  "updating": "Aggiornamento in corso...",
  "done": "Fatto!",
  "new_session_name": "Nome della nuova sessione (invio per annullare): ",
  "add_account": "Aggiungi account",
  "start_all": "Avvia tutto",
  "stop_all": "Arresta tutto",
  "sessions": "Sessioni",
  "start": "Avvia",
  "start_background": "Avvia in background",
  "delete_session": "Elimina sessione",
  "started": "Avviato.",
  "session_deleted": "Sessione eliminata.",
  "go_back": "Torna indietro",
  "exit": "Esci",
  "shitty_multithread_warning": "Attenzione! Il multithread non è stabile e potrebbe trasformarsi una forkbomb,,., vuoi continuare? (y/n) "
}
